stripe_referral/__init__.py
stripe_referral/py.typed
stripe_referral/adapters/__init__.py
stripe_referral/adapters/base.py
stripe_referral/adapters/manual.py
stripe_referral/adapters/stripe_connect.py
stripe_referral/adapters/wise.py
stripe_referral/config/__init__.py
stripe_referral/config/constants.py
stripe_referral/config/enums.py
stripe_referral/config/settings.py
stripe_referral/database/Base.py
stripe_referral/database/Session.py
stripe_referral/database/__init__.py
stripe_referral/exceptions/__init__.py
stripe_referral/exceptions/errors.py
stripe_referral/models/Payout.py
stripe_referral/models/ReferralCode.py
stripe_referral/models/ReferralProgram.py
stripe_referral/models/ReferralTracking.py
stripe_referral/models/__init__.py
stripe_referral/repositories/__init__.py
stripe_referral/repositories/base.py
stripe_referral/repositories/payout_repo.py
stripe_referral/repositories/program_repo.py
stripe_referral/repositories/referral_repo.py
stripe_referral/schemas/__init__.py
stripe_referral/schemas/payout.py
stripe_referral/schemas/referral.py
stripe_referral/schemas/types.py
stripe_referral/services/__init__.py
stripe_referral/services/payout_service.py
stripe_referral/services/referral_service.py
stripe_referral/utils/__init__.py
stripe_referral/utils/code_generator.py
stripe_referral-0.1.1.data/data/alembic.ini
stripe_referral-0.1.1.data/data/alembic/.gitkeep
stripe_referral-0.1.1.data/data/alembic/README
stripe_referral-0.1.1.data/data/alembic/env.py
stripe_referral-0.1.1.data/data/alembic/script.py.mako
stripe_referral-0.1.1.dist-info/licenses/LICENSE
stripe_referral-0.1.1.dist-info/METADATA
stripe_referral-0.1.1.dist-info/WHEEL
stripe_referral-0.1.1.dist-info/top_level.txt
stripe_referral-0.1.1.dist-info/RECORD
