Metadata-Version: 2.4
Name: stripe-referral
Version: 0.1.1
Summary: Framework agnostic referral program package with Stripe Connect integration
Author-email: CarterPerez-dev <carterperez@certgames.com>
License: MIT
Project-URL: Homepage, https://github.com/CarterPerez-dev/stripe-referral
Project-URL: Documentation, https://github.com/CarterPerez-dev/stripe-referral#readme
Project-URL: Repository, https://github.com/CarterPerez-dev/stripe-referral
Project-URL: Issues, https://github.com/CarterPerez-dev/stripe-referral/issues
Project-URL: Website, https://certgames.com
Keywords: referral,affiliate,code,stripe-code,stripe,stripe-connect,wise,payout,invite-code,saas,subscription,marketing
Classifier: Development Status :: 3 - Alpha
Classifier: Intended Audience :: Developers
Classifier: License :: OSI Approved :: MIT License
Classifier: Programming Language :: Python :: 3
Classifier: Programming Language :: Python :: 3.11
Classifier: Programming Language :: Python :: 3.12
Classifier: Topic :: Software Development :: Libraries :: Python Modules
Classifier: Topic :: Office/Business :: Financial
Classifier: Typing :: Typed
Requires-Python: >=3.11
License-File: LICENSE
Requires-Dist: alembic>=1.17.0
Requires-Dist: pydantic>=2.10.0
Requires-Dist: pydantic-settings>=2.10.0
Requires-Dist: python-dotenv>=1.0.0
Requires-Dist: sqlalchemy>=2.0.0
Requires-Dist: stripe>=12.0.0
Requires-Dist: psycopg2-binary>=2.9.0
Provides-Extra: dev
Requires-Dist: bandit[toml]==1.8.6; extra == "dev"
Requires-Dist: deptry==0.24.0; extra == "dev"
Requires-Dist: factory-boy==3.3.3; extra == "dev"
Requires-Dist: faker==38.0.0; extra == "dev"
Requires-Dist: freezegun==1.5.5; extra == "dev"
Requires-Dist: ipython==9.7.0; extra == "dev"
Requires-Dist: mypy==1.18.2; extra == "dev"
Requires-Dist: pip-audit==2.9.0; extra == "dev"
Requires-Dist: pip-tools==7.5.0; extra == "dev"
Requires-Dist: pre-commit==4.3.0; extra == "dev"
Requires-Dist: pytest==8.4.1; extra == "dev"
Requires-Dist: pytest-asyncio==1.3.0; extra == "dev"
Requires-Dist: pytest-cov==6.2.1; extra == "dev"
Requires-Dist: pytest-dotenv==0.5.2; extra == "dev"
Requires-Dist: pytest-env==1.1.5; extra == "dev"
Requires-Dist: pytest-mock==3.14.1; extra == "dev"
Requires-Dist: pylint==3.3.8; extra == "dev"
Requires-Dist: pylint-per-file-ignores==1.4.0; extra == "dev"
Requires-Dist: pylint-plugin-utils==0.9.0; extra == "dev"
Requires-Dist: pylint-pydantic==0.3.5; extra == "dev"
Requires-Dist: ruff==0.14.5; extra == "dev"
Requires-Dist: types-stripe==3.5.2.20240106; extra == "dev"
Requires-Dist: yapf==0.43.0; extra == "dev"
Provides-Extra: mysql
Requires-Dist: pymysql==1.1.2; extra == "mysql"
Requires-Dist: cryptography==46.0.3; extra == "mysql"
Dynamic: license-file
